harvestor/__init__.py
harvestor/config.py
harvestor/core/__init__.py
harvestor/core/cost_tracker.py
harvestor/core/harvestor.py
harvestor/extractors/__init__.py
harvestor/parsers/__init__.py
harvestor/parsers/llm_parser.py
harvestor/schemas/__init__.py
harvestor/schemas/base.py
harvestor/schemas/defaults.py
harvestor/schemas/prompt_builder.py
harvestor/storage/__init__.py
harvestor/tools/__init__.py
harvestor/validators/__init__.py
harvestor-0.0.1.dist-info/licenses/LICENSE
harvestor-0.0.1.dist-info/WHEEL
harvestor-0.0.1.dist-info/METADATA
harvestor-0.0.1.dist-info/RECORD
