Metadata-Version: 2.4
Name: harvestor
Version: 0.0.1
Summary: Harvest intelligence from any document - AI-powered data extraction and validation
Keywords: ai,llm,data-extraction,pdf,document-processing,ocr,anthropic,openai
Author: THUAUD Simon
Author-email: THUAUD Simon <sim.thuaud@gmail.com>
License-Expression: MIT
License-File: LICENSE
Classifier: Development Status :: 3 - Alpha
Classifier: Intended Audience :: Developers
Classifier: License :: OSI Approved :: MIT License
Classifier: Programming Language :: Python :: 3
Classifier: Programming Language :: Python :: 3.13
Classifier: Topic :: Scientific/Engineering :: Artificial Intelligence
Classifier: Topic :: Text Processing :: General
Requires-Dist: langchain>=0.1.0
Requires-Dist: langchain-anthropic>=0.1.0
Requires-Dist: langchain-openai>=0.0.5
Requires-Dist: anthropic>=0.18.0
Requires-Dist: openai>=1.10.0
Requires-Dist: pymupdf>=1.23.0
Requires-Dist: pdfplumber>=0.10.0
Requires-Dist: pillow>=10.2.0
Requires-Dist: pytesseract>=0.3.10
Requires-Dist: opencv-python-headless>=4.8.0
Requires-Dist: pydantic>=2.5.0
Requires-Dist: python-dotenv>=1.0.0
Requires-Dist: pyyaml>=6.0
Requires-Dist: sqlalchemy>=2.0.0
Requires-Dist: click>=8.1.0
Requires-Dist: rich>=13.7.0
Requires-Dist: tqdm>=4.66.0
Requires-Dist: pytest>=7.4.0 ; extra == 'dev'
Requires-Dist: pytest-mock>=3.12.0 ; extra == 'dev'
Requires-Dist: pytest-cov>=4.1.0 ; extra == 'dev'
Requires-Dist: ruff>=0.1.0 ; extra == 'dev'
Requires-Python: >=3.13, <3.14
Project-URL: Homepage, https://github.com/SIMOUNIX/harvestor
Project-URL: Repository, https://github.com/SIMOUNIX/harvestor
Project-URL: Issues, https://github.com/SIMOUNIX/harvestor/issues
Provides-Extra: dev
